aiotusclient/__init__.py
aiotusclient/baseuploader.py
aiotusclient/client.py
aiotusclient/exceptions.py
aiotusclient/py.typed
aiotusclient/request.py
aiotusclient/uploader.py
aiotusclient-0.1.4.dist-info/LICENSE
aiotusclient-0.1.4.dist-info/METADATA
aiotusclient-0.1.4.dist-info/WHEEL
aiotusclient-0.1.4.dist-info/top_level.txt
aiotusclient-0.1.4.dist-info/RECORD
