Metadata-Version: 2.1
Name: aiotusclient
Version: 0.1.4
Summary: tus.io-compatible upload client library for Python asyncio
Home-page: https://github.com/lablup/aiotusclient
Author: Lablup Inc.
Author-email: sergey@lablup.com
License: MIT
Project-URL: Source, https://github.com/lablup/aiotusclient
Project-URL: Tracker, https://github.com/lablup/aiotusclient/issues
Platform: UNKNOWN
Classifier: Development Status :: 3 - Alpha
Classifier: License :: OSI Approved :: MIT License
Classifier: Intended Audience :: Developers
Classifier: Programming Language :: Python
Classifier: Programming Language :: Python :: 3
Classifier: Programming Language :: Python :: 3.7
Classifier: Programming Language :: Python :: 3.8
Classifier: Operating System :: POSIX
Classifier: Operating System :: MacOS :: MacOS X
Classifier: Environment :: No Input/Output (Daemon)
Classifier: Topic :: Scientific/Engineering
Classifier: Topic :: Software Development
Requires-Python: >=3.7
Requires-Dist: aiohttp (>=3.6.2)
Requires-Dist: tqdm (>=4.42)
Provides-Extra: build
Requires-Dist: wheel (>=0.34.2) ; extra == 'build'
Requires-Dist: twine (>=3.2.0) ; extra == 'build'
Provides-Extra: ci
Provides-Extra: dev
Provides-Extra: lint
Requires-Dist: flake8 (>=3.8.3) ; extra == 'lint'
Provides-Extra: test
Requires-Dist: pytest (>=6.0.1) ; extra == 'test'
Requires-Dist: pytest-asyncio (>=0.14.0) ; extra == 'test'
Requires-Dist: pytest-cov (>=2.10.0) ; extra == 'test'
Requires-Dist: pytest-mock (>=3.2.0) ; extra == 'test'
Requires-Dist: codecov (>=2.1.8) ; extra == 'test'
Provides-Extra: typecheck
Requires-Dist: mypy (>=0.782) ; extra == 'typecheck'
